tbongkim03_cmd/__init__.py
tbongkim03_cmd/cmd.py
tbongkim03_cmd-0.2.1.dist-info/METADATA
tbongkim03_cmd-0.2.1.dist-info/WHEEL
tbongkim03_cmd-0.2.1.dist-info/entry_points.txt
tbongkim03_cmd-0.2.1.dist-info/top_level.txt
tbongkim03_cmd-0.2.1.dist-info/RECORD
