Metadata-Version: 2.1
Name: tbongkim03_cmd
Version: 0.2.1
Summary: Default template for PDM package
Author-email: tbongkim03 <tbongkim03@gmial.com>
License: MIT
Requires-Python: >=3.9
Requires-Dist: tbongkim03-lotto >=0.2.0
